{
"type": "FeatureCollection",
"name": "pod_sites",
"crs": { "type": "name", "properties": { "name": "urn:ogc:def:crs:OGC:1.3:CRS84" } },
"features": [
{ "type": "Feature", "properties": { "fid": 1, "pod_id": 1, "name": "Pleasant Valley High School Parking Lot", "lat": 40.923747569026915, "lon": -75.404488146571964 }, "geometry": { "type": "Point", "coordinates": [ -75.404488146571964, 40.923747569026915 ] } },
{ "type": "Feature", "properties": { "fid": 2, "pod_id": 2, "name": "Urgent Care Parking Lot", "lat": 41.147821908826955, "lon": -75.372391783481106 }, "geometry": { "type": "Point", "coordinates": [ -75.372391783481106, 41.147821908826955 ] } }
]
}
